{
  "version": 1,
  "serviceConfiguration": {
    "apiName": "TwitterClone",
    "serviceName": "AppSync",
    "gqlSchemaPath": "/tmp/amplify-343bbf57-ae95-4017-845e-a75d52803e52/amplify/backend/api/TwitterClone/schema.graphql",
    "defaultAuthType": {
      "mode": "API_KEY",
      "keyDescription": "api key description",
      "expirationTime": 30
    },
    "additionalAuthTypes": [
      {
        "mode": "AWS_IAM"
      }
    ],
    "conflictResolution": {
      "defaultResolutionStrategy": {
        "type": "AUTOMERGE"
      }
    }
  }
}